{
    "meta": {
        "id": "I1J7dsWZSonbYyJNqVAOlOxK1CM=",
        "test": false,
        "prepared": "2022-09-10 08:35:59 1165",
        "sender": {
            "id": "dgbas",
            "name": "行政院主計總處"
        },
        "links": [
            {
                "href": "https:\/\/nstatdb.dgbas.gov.tw\/dgbasAll\/webMain.aspx?sdmx\/A018703010\/\/",
                "rel": "request"
            }
        ]
    },
    "data": {
        "dataSets": [
            {
                "action": "Information",
                "series": {
                    "0": {
                        "observations": {
                            "0": [
                                3996649
                            ],
                            "1": [
                                4287685
                            ],
                            "2": [
                                4496818
                            ],
                            "3": [
                                4657998
                            ],
                            "4": [
                                4900195
                            ],
                            "5": [
                                4852251
                            ],
                            "6": [
                                4859348
                            ],
                            "7": [
                                5024645
                            ],
                            "8": [
                                5260734
                            ],
                            "9": [
                                5510486
                            ],
                            "10": [
                                5774724
                            ],
                            "11": [
                                5945831
                            ],
                            "12": [
                                6029730
                            ],
                            "13": [
                                5785122
                            ],
                            "14": [
                                6171668
                            ],
                            "15": [
                                6470507
                            ],
                            "16": [
                                6661640
                            ],
                            "17": [
                                6814940
                            ],
                            "18": [
                                7208012
                            ],
                            "19": [
                                7525226
                            ],
                            "20": [
                                7745448
                            ],
                            "21": [
                                8031111
                            ]
                        }
                    },
                    "1": {
                        "observations": {
                            "0": [
                                1814560
                            ],
                            "1": [
                                1926137
                            ],
                            "2": [
                                2138899
                            ],
                            "3": [
                                2364067
                            ],
                            "4": [
                                2552351
                            ],
                            "5": [
                                2606919
                            ],
                            "6": [
                                2674545
                            ],
                            "7": [
                                2641255
                            ],
                            "8": [
                                2735085
                            ],
                            "9": [
                                2803770
                            ],
                            "10": [
                                3050407
                            ],
                            "11": [
                                3207266
                            ],
                            "12": [
                                3065066
                            ],
                            "13": [
                                2985798
                            ],
                            "14": [
                                3116255
                            ],
                            "15": [
                                3089041
                            ],
                            "16": [
                                3162251
                            ],
                            "17": [
                                3183298
                            ],
                            "18": [
                                3578289
                            ],
                            "19": [
                                3529652
                            ],
                            "20": [
                                3483540
                            ],
                            "21": [
                                3466285
                            ]
                        }
                    },
                    "2": {
                        "observations": {
                            "0": [
                                516950
                            ],
                            "1": [
                                593172
                            ],
                            "2": [
                                604165
                            ],
                            "3": [
                                719420
                            ],
                            "4": [
                                728200
                            ],
                            "5": [
                                782981
                            ],
                            "6": [
                                802279
                            ],
                            "7": [
                                762963
                            ],
                            "8": [
                                838960
                            ],
                            "9": [
                                951965
                            ],
                            "10": [
                                1016677
                            ],
                            "11": [
                                1067057
                            ],
                            "12": [
                                1246113
                            ],
                            "13": [
                                1166937
                            ],
                            "14": [
                                1155879
                            ],
                            "15": [
                                1223210
                            ],
                            "16": [
                                1418194
                            ],
                            "17": [
                                1517493
                            ],
                            "18": [
                                1531967
                            ],
                            "19": [
                                1652202
                            ],
                            "20": [
                                1671534
                            ],
                            "21": [
                                1831523
                            ]
                        }
                    },
                    "3": {
                        "observations": {
                            "0": [
                                67849
                            ],
                            "1": [
                                80914
                            ],
                            "2": [
                                94982
                            ],
                            "3": [
                                97488
                            ],
                            "4": [
                                95642
                            ],
                            "5": [
                                85276
                            ],
                            "6": [
                                88488
                            ],
                            "7": [
                                90969
                            ],
                            "8": [
                                103554
                            ],
                            "9": [
                                110342
                            ],
                            "10": [
                                124504
                            ],
                            "11": [
                                150060
                            ],
                            "12": [
                                171860
                            ],
                            "13": [
                                162305
                            ],
                            "14": [
                                167065
                            ],
                            "15": [
                                164496
                            ],
                            "16": [
                                163362
                            ],
                            "17": [
                                183360
                            ],
                            "18": [
                                201147
                            ],
                            "19": [
                                208742
                            ],
                            "20": [
                                221401
                            ],
                            "21": [
                                216815
                            ]
                        }
                    },
                    "4": {
                        "observations": {
                            "0": [
                                6396008
                            ],
                            "1": [
                                6887908
                            ],
                            "2": [
                                7334864
                            ],
                            "3": [
                                7838973
                            ],
                            "4": [
                                8276388
                            ],
                            "5": [
                                8327427
                            ],
                            "6": [
                                8424660
                            ],
                            "7": [
                                8519832
                            ],
                            "8": [
                                8938333
                            ],
                            "9": [
                                9376563
                            ],
                            "10": [
                                9966312
                            ],
                            "11": [
                                10370214
                            ],
                            "12": [
                                10512769
                            ],
                            "13": [
                                10100162
                            ],
                            "14": [
                                10610867
                            ],
                            "15": [
                                10947254
                            ],
                            "16": [
                                11405447
                            ],
                            "17": [
                                11699091
                            ],
                            "18": [
                                12519415
                            ],
                            "19": [
                                12915822
                            ],
                            "20": [
                                13121923
                            ],
                            "21": [
                                13545734
                            ]
                        }
                    },
                    "5": {
                        "observations": {
                            "0": [
                                4372030
                            ],
                            "1": [
                                4742938
                            ],
                            "2": [
                                5116174
                            ],
                            "3": [
                                5393982
                            ],
                            "4": [
                                5705842
                            ],
                            "5": [
                                5755500
                            ],
                            "6": [
                                5952563
                            ],
                            "7": [
                                6098448
                            ],
                            "8": [
                                6488097
                            ],
                            "9": [
                                6780122
                            ],
                            "10": [
                                6942614
                            ],
                            "11": [
                                7191198
                            ],
                            "12": [
                                7250351
                            ],
                            "13": [
                                7162577
                            ],
                            "14": [
                                7481002
                            ],
                            "15": [
                                7774972
                            ],
                            "16": [
                                8015850
                            ],
                            "17": [
                                8242378
                            ],
                            "18": [
                                8602842
                            ],
                            "19": [
                                8787564
                            ],
                            "20": [
                                9082075
                            ],
                            "21": [
                                9325676
                            ]
                        }
                    },
                    "6": {
                        "observations": {
                            "0": [
                                314167
                            ],
                            "1": [
                                366960
                            ],
                            "2": [
                                315764
                            ],
                            "3": [
                                331015
                            ],
                            "4": [
                                313455
                            ],
                            "5": [
                                290362
                            ],
                            "6": [
                                281499
                            ],
                            "7": [
                                262734
                            ],
                            "8": [
                                280459
                            ],
                            "9": [
                                372318
                            ],
                            "10": [
                                406597
                            ],
                            "11": [
                                415064
                            ],
                            "12": [
                                445513
                            ],
                            "13": [
                                361168
                            ],
                            "14": [
                                379292
                            ],
                            "15": [
                                425444
                            ],
                            "16": [
                                481032
                            ],
                            "17": [
                                499803
                            ],
                            "18": [
                                515427
                            ],
                            "19": [
                                580542
                            ],
                            "20": [
                                581666
                            ],
                            "21": [
                                579614
                            ]
                        }
                    },
                    "7": {
                        "observations": {
                            "0": [
                                664815
                            ],
                            "1": [
                                707025
                            ],
                            "2": [
                                749363
                            ],
                            "3": [
                                807455
                            ],
                            "4": [
                                855600
                            ],
                            "5": [
                                893502
                            ],
                            "6": [
                                934414
                            ],
                            "7": [
                                979764
                            ],
                            "8": [
                                1028857
                            ],
                            "9": [
                                1115629
                            ],
                            "10": [
                                1212098
                            ],
                            "11": [
                                1218919
                            ],
                            "12": [
                                1254150
                            ],
                            "13": [
                                1332931
                            ],
                            "14": [
                                1409349
                            ],
                            "15": [
                                1496473
                            ],
                            "16": [
                                1562564
                            ],
                            "17": [
                                1667258
                            ],
                            "18": [
                                1716146
                            ],
                            "19": [
                                1784329
                            ],
                            "20": [
                                1943185
                            ],
                            "21": [
                                1903904
                            ]
                        }
                    },
                    "8": {
                        "observations": {
                            "0": [
                                135258
                            ],
                            "1": [
                                145036
                            ],
                            "2": [
                                147876
                            ],
                            "3": [
                                173742
                            ],
                            "4": [
                                180039
                            ],
                            "5": [
                                179209
                            ],
                            "6": [
                                175246
                            ],
                            "7": [
                                183075
                            ],
                            "8": [
                                230606
                            ],
                            "9": [
                                246781
                            ],
                            "10": [
                                250602
                            ],
                            "11": [
                                275389
                            ],
                            "12": [
                                258926
                            ],
                            "13": [
                                232846
                            ],
                            "14": [
                                248524
                            ],
                            "15": [
                                270791
                            ],
                            "16": [
                                238409
                            ],
                            "17": [
                                271601
                            ],
                            "18": [
                                284850
                            ],
                            "19": [
                                315985
                            ],
                            "20": [
                                323389
                            ],
                            "21": [
                                342301
                            ]
                        }
                    },
                    "9": {
                        "observations": {
                            "0": [
                                5486270
                            ],
                            "1": [
                                5961959
                            ],
                            "2": [
                                6329177
                            ],
                            "3": [
                                6706194
                            ],
                            "4": [
                                7054936
                            ],
                            "5": [
                                7118573
                            ],
                            "6": [
                                7343722
                            ],
                            "7": [
                                7524021
                            ],
                            "8": [
                                8028019
                            ],
                            "9": [
                                8514850
                            ],
                            "10": [
                                8811911
                            ],
                            "11": [
                                9100570
                            ],
                            "12": [
                                9208940
                            ],
                            "13": [
                                9089522
                            ],
                            "14": [
                                9518167
                            ],
                            "15": [
                                9967680
                            ],
                            "16": [
                                10297855
                            ],
                            "17": [
                                10681040
                            ],
                            "18": [
                                11119265
                            ],
                            "19": [
                                11468420
                            ],
                            "20": [
                                11930315
                            ],
                            "21": [
                                12151495
                            ]
                        }
                    },
                    "10": {
                        "observations": {
                            "0": [
                                909738
                            ],
                            "1": [
                                925949
                            ],
                            "2": [
                                1005687
                            ],
                            "3": [
                                1132779
                            ],
                            "4": [
                                1221452
                            ],
                            "5": [
                                1208854
                            ],
                            "6": [
                                1080938
                            ],
                            "7": [
                                995811
                            ],
                            "8": [
                                910314
                            ],
                            "9": [
                                861713
                            ],
                            "10": [
                                1154401
                            ],
                            "11": [
                                1269644
                            ],
                            "12": [
                                1303829
                            ],
                            "13": [
                                1010640
                            ],
                            "14": [
                                1092700
                            ],
                            "15": [
                                979574
                            ],
                            "16": [
                                1107592
                            ],
                            "17": [
                                1018051
                            ],
                            "18": [
                                1400150
                            ],
                            "19": [
                                1447402
                            ],
                            "20": [
                                1191608
                            ],
                            "21": [
                                1394239
                            ]
                        }
                    },
                    "11": {
                        "observations": {
                            "0": [
                                5281768
                            ],
                            "1": [
                                5668887
                            ],
                            "2": [
                                6121861
                            ],
                            "3": [
                                6526761
                            ],
                            "4": [
                                6927294
                            ],
                            "5": [
                                6964354
                            ],
                            "6": [
                                7033501
                            ],
                            "7": [
                                7094259
                            ],
                            "8": [
                                7398411
                            ],
                            "9": [
                                7641835
                            ],
                            "10": [
                                8097015
                            ],
                            "11": [
                                8460842
                            ],
                            "12": [
                                8554180
                            ],
                            "13": [
                                8173217
                            ],
                            "14": [
                                8573702
                            ],
                            "15": [
                                8754546
                            ],
                            "16": [
                                9123442
                            ],
                            "17": [
                                9260429
                            ],
                            "18": [
                                10002992
                            ],
                            "19": [
                                10234966
                            ],
                            "20": [
                                10273683
                            ],
                            "21": [
                                10719915
                            ]
                        }
                    }
                }
            }
        ],
        "structure": {
            "links": [
                {
                    "href": "https:\/\/nstatdb.dgbas.gov.tw\/dgbasAll\/webMain.aspx?sdmx\/A018703010\/all",
                    "rel": "dataflow"
                }
            ],
            "name": "家庭及民間非營利機構之收支",
            "dimensions": {
                "series": [
                    {
                        "keyPosition": 0,
                        "id": "fldid",
                        "name": "收支項（當期價格）",
                        "values": [
                            {
                                "id": "1",
                                "name": "1.受僱人員報酬"
                            },
                            {
                                "id": "2",
                                "name": "2.財產與企業所得淨額"
                            },
                            {
                                "id": "3",
                                "name": "3.國內經常移轉收入"
                            },
                            {
                                "id": "4",
                                "name": "4.國外經常移轉收入"
                            },
                            {
                                "id": "5",
                                "name": "5.所得 (5=1+...+4)"
                            },
                            {
                                "id": "6",
                                "name": "6.民間消費"
                            },
                            {
                                "id": "7",
                                "name": "7.所得稅與其他經常稅"
                            },
                            {
                                "id": "8",
                                "name": "8.其他國內經常移轉支出"
                            },
                            {
                                "id": "9",
                                "name": "9.國外經常移轉支出"
                            },
                            {
                                "id": "10",
                                "name": "10.支出 (10=6+...+9)"
                            },
                            {
                                "id": "11",
                                "name": "11.儲蓄 (11=5-10)"
                            },
                            {
                                "id": "12",
                                "name": "12.可支配所得 (12=5-7-8-9)"
                            }
                        ],
                        "role": "REF_FLDID"
                    }
                ],
                "observation": [
                    {
                        "id": "ym",
                        "name": "統計期",
                        "values": [
                            {
                                "id": "1996",
                                "name": "85年"
                            },
                            {
                                "id": "1997",
                                "name": "86年"
                            },
                            {
                                "id": "1998",
                                "name": "87年"
                            },
                            {
                                "id": "1999",
                                "name": "88年"
                            },
                            {
                                "id": "2000",
                                "name": "89年"
                            },
                            {
                                "id": "2001",
                                "name": "90年"
                            },
                            {
                                "id": "2002",
                                "name": "91年"
                            },
                            {
                                "id": "2003",
                                "name": "92年"
                            },
                            {
                                "id": "2004",
                                "name": "93年"
                            },
                            {
                                "id": "2005",
                                "name": "94年"
                            },
                            {
                                "id": "2006",
                                "name": "95年"
                            },
                            {
                                "id": "2007",
                                "name": "96年"
                            },
                            {
                                "id": "2008",
                                "name": "97年"
                            },
                            {
                                "id": "2009",
                                "name": "98年"
                            },
                            {
                                "id": "2010",
                                "name": "99年"
                            },
                            {
                                "id": "2011",
                                "name": "100年"
                            },
                            {
                                "id": "2012",
                                "name": "101年"
                            },
                            {
                                "id": "2013",
                                "name": "102年"
                            },
                            {
                                "id": "2014",
                                "name": "103年"
                            },
                            {
                                "id": "2015",
                                "name": "104年"
                            },
                            {
                                "id": "2016",
                                "name": "105年"
                            },
                            {
                                "id": "2017",
                                "name": "106年"
                            }
                        ],
                        "role": "TIME_PERIOD"
                    }
                ]
            }
        }
    }
}